django_wikidata/__init__.py
django_wikidata/entity.py
django_wikidata/fields.py
django_wikidata/forms.py
django_wikidata/mixins.py
django_wikidata/validators.py
django_wikidata/widgets.py
django_wikidata-0.0.6.dist-info/METADATA
django_wikidata-0.0.6.dist-info/WHEEL
django_wikidata-0.0.6.dist-info/top_level.txt
django_wikidata-0.0.6.dist-info/RECORD
