Metadata-Version: 2.1
Name: django-wikidata
Version: 0.0.6
Summary: Django Wikidata integration
Home-page: https://github.com/stefanw/django-wikidata
Author: Stefan Wehrmeyer
Author-email: mail@stefanwehrmeyer.com
License: MIT
Platform: UNKNOWN
Classifier: Development Status :: 1 - Planning
Classifier: Environment :: Web Environment
Classifier: Framework :: Django
Classifier: Intended Audience :: Developers
Classifier: License :: OSI Approved :: MIT License
Classifier: Natural Language :: English
Classifier: Operating System :: OS Independent
Classifier: Programming Language :: Python :: 3
Classifier: Topic :: Internet :: WWW/HTTP
Requires-Dist: Django
Requires-Dist: wikidata
